qilimanjaro_portfolio/__init__.py
qilimanjaro_portfolio/algorithm.py
qilimanjaro_portfolio/program.py
qilimanjaro_portfolio/bellstate/__init__.py
qilimanjaro_portfolio/bellstate/bellstate.py
qilimanjaro_portfolio/udmis/__init__.py
qilimanjaro_portfolio/udmis/plot_aux.py
qilimanjaro_portfolio/udmis/typings.py
qilimanjaro_portfolio/udmis/udmis.py
qilimanjaro_portfolio/udmis/tests/__init__.py
qilimanjaro_portfolio/udmis/tests/data.py
qilimanjaro_portfolio/udmis/tests/test_udmis.py
qilimanjaro_portfolio-0.0.1.dist-info/LICENSE
qilimanjaro_portfolio-0.0.1.dist-info/METADATA
qilimanjaro_portfolio-0.0.1.dist-info/WHEEL
qilimanjaro_portfolio-0.0.1.dist-info/top_level.txt
qilimanjaro_portfolio-0.0.1.dist-info/RECORD
