Metadata-Version: 2.1
Name: qilimanjaro-portfolio
Version: 0.0.1
Summary: Qilimanjaro Portfolio Library
Home-page: https://github.com/qilimanjaro-tech/qili-portfolio-library
Author: Qilimanjaro team
Author-email: info@qilimanjaro.tech
License: UNKNOWN
Platform: UNKNOWN
Classifier: Programming Language :: Python :: 3
Classifier: Topic :: Scientific/Engineering :: Physics
Requires-Python: >=3.6.0
License-File: LICENSE
Requires-Dist: qilimanjaroq-client
Provides-Extra: docs
Requires-Dist: sphinx ; extra == 'docs'
Requires-Dist: sphinx-rtd-theme ; extra == 'docs'
Requires-Dist: recommonmark ; extra == 'docs'
Requires-Dist: sphinxcontrib-bibtex ; extra == 'docs'
Requires-Dist: sphinx-markdown-tables ; extra == 'docs'
Requires-Dist: nbsphinx ; extra == 'docs'
Requires-Dist: IPython ; extra == 'docs'
Provides-Extra: tests
Requires-Dist: pytest ; extra == 'tests'
